{
  "number": "0001",
  "slug": "initializing-the-broadcast",
  "title": "Post 0001 — Initializing the Broadcast",
  "subtitle": "Beginning the public technical record",
  "summary": "The first public field dispatch establishing the blog as a long-form record for systems architecture, Bitcoin, software, firmware, hardware, artificial intelligence, cybersecurity, OSINT, research, and development.",
  "published": "2025-06-01T03:33:00-04:00",
  "updated": "2025-06-01T03:33:00-04:00",
  "author": "0xdeadbeef",
  "category": "Development",
  "tags": [
    "Artificial Intelligence",
    "Bitcoin",
    "Cybersecurity",
    "Development",
    "Research",
    "ZZX-Labs"
  ],
  "status": "Published",
  "featured": true,
  "license": "All rights reserved unless otherwise stated.",
  "copyright": "© 2025 0xdeadbeef",
  "revision": "1.0",
  "hash_algorithm": "",
  "hash": "",
  "signature_algorithm": "",
  "signature_url": "",
  "source_url": "",
  "url": "/blog/blog_posts/post_0001/",
  "text_url": "./post.txt",
  "metadata_url": "./metadata.json",
  "published_to_index": true
}
